<sect1 id="Layout.LinLog">
	<title>LinLog</title>
	<para>
		LinLog algorithm for concept layout. It is possible to define
		edge attributes for clustering purposes if all edge have these
		attributes.
	</para>
	<para>
		<screenshot>
			<mediaobject>
				<imageobject>
					<imagedata fileref="../images/layout/layout_linLog.png"
						align="center" />
				</imageobject>
			</mediaobject>
		</screenshot>
	</para>
	<para>
		For more information visit
		<ulink url="http://www.informatik.tu-cottbus.de/~an/GD/linlog.html">
			http://www.informatik.tu-cottbus.de/~an/GD/linlog.html
		</ulink>
		.
	</para>
</sect1>