<sect1 id="Filter.Defluff">
	<title>Defluff</title>
	<para>
		This filter allows users to filter out single-linked chains which end in
		unconnected nodes.
	</para>
	<para>
		<screenshot>
			<mediaobject>
				<imageobject>
					<imagedata align="center" fileref="../images/filter/filter_defluff1.png" />
				</imageobject>
			</mediaobject>
		</screenshot>
	</para>
	<para>
		After applying the defluff filter
	</para>
	<para>
		<screenshot>
			<mediaobject>
				<imageobject>
					<imagedata align="center" fileref="../images/filter/filter_defluff2.png" />
				</imageobject>
			</mediaobject>
		</screenshot>
	</para>
</sect1>