<sect1 id="Layout.AttributeKK">
	<title>Kamada-Kawai</title>
	<para>
		Kamada-Kawai algorithm for concept layout. It is possible to use
		attribute value for preferred edge length.
	</para>
	<para>
		<screenshot>
			<mediaobject>
				<imageobject>
					<imagedata fileref="../images/layout/layout_kamadaKawai.png"
						align="center" />
				</imageobject>
			</mediaobject>
		</screenshot>
	</para>
	<para>
		For more information see
		<ulink
			url="http://www.sciencedirect.com/science/article/pii/0020019089901026">
			<citetitle>
				An algorithm for drawing general undirected graphs
			</citetitle>
		</ulink>
		.
	</para>
</sect1>